pyg4i/__init__.py
pyg4i/g4i.py
pyg4i-0.2.2.dist-info/METADATA
pyg4i-0.2.2.dist-info/WHEEL
pyg4i-0.2.2.dist-info/top_level.txt
pyg4i-0.2.2.dist-info/RECORD
